ripple1d/__init__.py
ripple1d/consts.py
ripple1d/data_model.py
ripple1d/errors.py
ripple1d/ras.py
ripple1d/rasmap.py
ripple1d/ripple1d_logger.py
ripple1d/version.py
ripple1d/api/__init__.py
ripple1d/api/app.py
ripple1d/api/log.py
ripple1d/api/manager.py
ripple1d/api/run_api_test.py
ripple1d/api/tasks.py
ripple1d/api/utils.py
ripple1d/api/static/css/main.css
ripple1d/api/static/img/favicon-32x32.png
ripple1d/api/static/svgs/check-icon.svg
ripple1d/api/static/svgs/cross-icon.svg
ripple1d/api/static/svgs/delete-icon.svg
ripple1d/api/static/svgs/yellow-circle-icon.svg
ripple1d/api/templates/jobs.html
ripple1d/conflate/__init__.py
ripple1d/conflate/rasfim.py
ripple1d/hecstac/__init__.py
ripple1d/hecstac/ras_to_gpkg.py
ripple1d/hecstac/common/__init__.py
ripple1d/hecstac/common/asset_factory.py
ripple1d/hecstac/common/base_io.py
ripple1d/hecstac/common/consts.py
ripple1d/hecstac/common/geometry.py
ripple1d/hecstac/common/path_manager.py
ripple1d/hecstac/common/s3_utils.py
ripple1d/hecstac/ras/__init__.py
ripple1d/hecstac/ras/assets.py
ripple1d/hecstac/ras/consts.py
ripple1d/hecstac/ras/errors.py
ripple1d/hecstac/ras/item.py
ripple1d/hecstac/ras/parser.py
ripple1d/hecstac/ras/utils.py
ripple1d/ops/__init__.py
ripple1d/ops/endpoints.py
ripple1d/ops/fim_lib.py
ripple1d/ops/metrics.py
ripple1d/ops/ras_conflate.py
ripple1d/ops/ras_run.py
ripple1d/ops/ras_terrain.py
ripple1d/ops/subset_gpkg.py
ripple1d/utils/__init__.py
ripple1d/utils/dg_utils.py
ripple1d/utils/gpkg_utils.py
ripple1d/utils/ripple_utils.py
ripple1d/utils/s3_utils.py
ripple1d/utils/sqlite_utils.py
ripple1d/utils/stac_utils.py
ripple1d-0.10.4.dist-info/licenses/LICENSE
ripple1d-0.10.4.dist-info/METADATA
ripple1d-0.10.4.dist-info/WHEEL
ripple1d-0.10.4.dist-info/entry_points.txt
ripple1d-0.10.4.dist-info/top_level.txt
ripple1d-0.10.4.dist-info/RECORD
