Metadata-Version: 2.4
Name: ripple1d
Version: 0.10.4
Summary: HEC-RAS model automation
Maintainer-email: Seth Lawler <slawler@dewberry.com>, Matt Deshotel <mdeshotel@dewberry.com>, Scott Lawson <klawson@dewberry.com>, Abdul Siddiqui <abdul.siddiqui@ertcorp.com>
Project-URL: repository, https://github.com/dewberry/ripple1d
Classifier: Development Status :: 4 - Beta
Classifier: Intended Audience :: Developers
Classifier: License :: OSI Approved :: MIT License
Classifier: Programming Language :: Python :: 3
Classifier: Programming Language :: Python :: 3.10
Classifier: Programming Language :: Python :: 3.11
Classifier: Programming Language :: Python :: 3.12
License-File: LICENSE
Requires-Dist: boto3==1.35.0
Requires-Dist: contextily==1.6.0
Requires-Dist: python-dotenv
Requires-Dist: flask==3.0.3
Requires-Dist: fiona==1.9.6
Requires-Dist: h5py==3.11.0
Requires-Dist: huey==2.5.1
Requires-Dist: geopandas==1.0.1
Requires-Dist: matplotlib==3.9.0
Requires-Dist: mypy_boto3_s3==1.34.120
Requires-Dist: numpy==2.0.1
Requires-Dist: psutil==6.0.0
Requires-Dist: pystac==1.13.0
Requires-Dist: pyarrow==16.1.0
Requires-Dist: rasterio==1.3.10
Requires-Dist: requests==2.32.3
Requires-Dist: shapely==2.0.5
Requires-Dist: xarray==2024.11.0
Requires-Dist: rioxarray==0.18.1
Requires-Dist: rashdf==0.8.2
Requires-Dist: typing_extensions==4.14.1
Requires-Dist: obstore==0.6.0
Provides-Extra: dev
Requires-Dist: pre-commit; extra == "dev"
Requires-Dist: ruff; extra == "dev"
Requires-Dist: pytest; extra == "dev"
Requires-Dist: pytest-cov; extra == "dev"
Requires-Dist: pytest-json-report; extra == "dev"
Provides-Extra: docs
Requires-Dist: sphinx; extra == "docs"
Requires-Dist: numpydoc; extra == "docs"
Requires-Dist: sphinx_rtd_theme; extra == "docs"
Requires-Dist: sphinx_design; extra == "docs"
Requires-Dist: pydata-sphinx-theme; extra == "docs"
Requires-Dist: sphinx-autodoc-typehints; extra == "docs"
Requires-Dist: myst-parser; extra == "docs"
Dynamic: license-file
